mkdocs_drawio_url/plugin.py
mkdocs_drawio_url-1.0.1.dist-info/LICENSE
mkdocs_drawio_url-1.0.1.dist-info/METADATA
mkdocs_drawio_url-1.0.1.dist-info/WHEEL
mkdocs_drawio_url-1.0.1.dist-info/entry_points.txt
mkdocs_drawio_url-1.0.1.dist-info/RECORD
