Metadata-Version: 2.1
Name: mkdocs-drawio-url
Version: 1.0.1
Summary: MkDocs plugin for displaying draw io file with url
Home-page: https://github.com/sylvain121/mkdocs-drawio-url/
License: MIT
Keywords: mkdocs,plugin,markdown,drawio
Author: Sergey Lukin
Author-email: onixpro@gmail.com
Requires-Python: >=3.9,<4.0
Classifier: License :: OSI Approved :: MIT License
Classifier: Programming Language :: Python :: 3
Classifier: Programming Language :: Python :: 3.9
Classifier: Programming Language :: Python :: 3.10
Classifier: Programming Language :: Python :: 3.11
Classifier: Programming Language :: Python :: 3.12
Requires-Dist: Jinja2 (>=3.0)
Requires-Dist: beautifulsoup4 (>=4.0)
Requires-Dist: lxml (>=4.0)
Requires-Dist: mkdocs (>=1.3)
Requires-Dist: requests (>=2.0)
Project-URL: Repository, https://github.com/sylvain121/mkdocs-drawio-url/
